README.md
setup.cfg
setup.py
keychest_agent/__init__.py
keychest_agent/agent.py
keychest_agent/config.py
keychest_agent/core.py
keychest_agent/internal_comm.py
keychest_agent/log_dispatcher.py
keychest_agent/logger.py
keychest_agent/main.py
keychest_agent/misc.py
keychest_agent/proxy.py
keychest_agent/security.py
keychest_agent/threadpool.py
keychest_agent/version.py
keychest_agent/winmain.py
keychest_agent.egg-info/PKG-INFO
keychest_agent.egg-info/SOURCES.txt
keychest_agent.egg-info/dependency_links.txt
keychest_agent.egg-info/entry_points.txt
keychest_agent.egg-info/namespace_packages.txt
keychest_agent.egg-info/requires.txt
keychest_agent.egg-info/top_level.txt
keychest_agent/pyaes/__init__.py
keychest_agent/pyaes/aespy.py
keychest_agent/pyaes/blockfeeder.py
keychest_agent/pyaes/util.py