Metadata-Version: 2.1
Name: keychest-agent
Version: 1.3.13
Summary: Keychest agent
Home-page: https://gitlab.com/keychest/agent
Author: Smart Arcs Ltd
Author-email: support@keychest.net
License: UNKNOWN
Platform: UNKNOWN
Classifier: Development Status :: 3 - Alpha
Classifier: Intended Audience :: Developers
Classifier: Programming Language :: Python
Classifier: Programming Language :: Python :: 3
Classifier: Programming Language :: Python :: 3.6
Classifier: Programming Language :: Python :: 3.7
Classifier: License :: OSI Approved :: GNU General Public License v3 (GPLv3)
Classifier: Topic :: Internet :: WWW/HTTP
Classifier: Topic :: Security
Provides-Extra: dev
Provides-Extra: docs
